{"tileChips":[{"turnFaceType":0,"tileId":5,"isAdvance":false,"isInvert":false,"isRope":false,"isStone":false,"isPlayer":false},{"turnFaceType":0,"tileId":5,"isAdvance":false,"isInvert":false,"isRope":false,"isStone":false,"isPlayer":false},{"turnFaceType":0,"tileId":5,"isAdvance":false,"isInvert":false,"isRope":false,"isStone":false,"isPlayer":false},{"turnFaceType":0,"tileId":5,"isAdvance":false,"isInvert":false,"isRope":false,"isStone":false,"isPlayer":false},{"turnFaceType":0,"tileId":5,"isAdvance":false,"isInvert":false,"isRope":false,"isStone":false,"isPlayer":false},{"turnFaceType":0,"tileId":5,"isAdvance":false,"isInvert":false,"isRope":false,"isStone":false,"isPlayer":false},{"turnFaceType":0,"tileId":5,"isAdvance":false,"isInvert":false,"isRope":false,"isStone":false,"isPlayer":false},{"turnFaceType":0,"tileId":0,"isAdvance":false,"isInvert":false,"isRope":false,"isStone":false,"isPlayer":false},{"turnFaceType":0,"tileId":5,"isAdvance":false,"isInvert":false,"isRope":false,"isStone":false,"isPlayer":false},{"turnFaceType":0,"tileId":4,"isAdvance":false,"isInvert":true,"isRope":false,"isStone":false,"isPlayer":false},{"turnFaceType":0,"tileId":1,"isAdvance":true,"isInvert":true,"isRope":false,"isStone":false,"isPlayer":false},{"turnFaceType":0,"tileId":7,"isAdvance":false,"isInvert":true,"isRope":false,"isStone":false,"isPlayer":false},{"turnFaceType":0,"tileId":1,"isAdvance":true,"isInvert":true,"isRope":false,"isStone":false,"isPlayer":false},{"turnFaceType":0,"tileId":4,"isAdvance":false,"isInvert":true,"isRope":false,"isStone":false,"isPlayer":false},{"turnFaceType":0,"tileId":5,"isAdvance":false,"isInvert":false,"isRope":false,"isStone":false,"isPlayer":false},{"turnFaceType":0,"tileId":0,"isAdvance":false,"isInvert":false,"isRope":false,"isStone":false,"isPlayer":false},{"turnFaceType":0,"tileId":5,"isAdvance":false,"isInvert":false,"isRope":false,"isStone":false,"isPlayer":false},{"turnFaceType":0,"tileId":4,"isAdvance":false,"isInvert":true,"isRope":false,"isStone":false,"isPlayer":false},{"turnFaceType":0,"tileId":4,"isAdvance":false,"isInvert":true,"isRope":false,"isStone":false,"isPlayer":false},{"turnFaceType":0,"tileId":1,"isAdvance":true,"isInvert":true,"isRope":false,"isStone":false,"isPlayer":false},{"turnFaceType":0,"tileId":4,"isAdvance":false,"isInvert":true,"isRope":false,"isStone":false,"isPlayer":false},{"turnFaceType":0,"tileId":1,"isAdvance":true,"isInvert":true,"isRope":false,"isStone":false,"isPlayer":false},{"turnFaceType":0,"tileId":5,"isAdvance":false,"isInvert":false,"isRope":false,"isStone":false,"isPlayer":false},{"turnFaceType":0,"tileId":0,"isAdvance":false,"isInvert":false,"isRope":false,"isStone":false,"isPlayer":false},{"turnFaceType":0,"tileId":5,"isAdvance":false,"isInvert":false,"isRope":false,"isStone":false,"isPlayer":false},{"turnFaceType":0,"tileId":1,"isAdvance":true,"isInvert":true,"isRope":false,"isStone":false,"isPlayer":false},{"turnFaceType":0,"tileId":1,"isAdvance":true,"isInvert":true,"isRope":false,"isStone":false,"isPlayer":false},{"turnFaceType":0,"tileId":4,"isAdvance":false,"isInvert":true,"isRope":false,"isStone":false,"isPlayer":false},{"turnFaceType":0,"tileId":1,"isAdvance":true,"isInvert":true,"isRope":false,"isStone":false,"isPlayer":true},{"turnFaceType":0,"tileId":4,"isAdvance":false,"isInvert":true,"isRope":false,"isStone":false,"isPlayer":false},{"turnFaceType":0,"tileId":5,"isAdvance":false,"isInvert":false,"isRope":false,"isStone":false,"isPlayer":false},{"turnFaceType":0,"tileId":0,"isAdvance":false,"isInvert":false,"isRope":false,"isStone":false,"isPlayer":false},{"turnFaceType":0,"tileId":5,"isAdvance":false,"isInvert":false,"isRope":false,"isStone":false,"isPlayer":false},{"turnFaceType":0,"tileId":4,"isAdvance":false,"isInvert":true,"isRope":false,"isStone":false,"isPlayer":false},{"turnFaceType":0,"tileId":4,"isAdvance":false,"isInvert":true,"isRope":false,"isStone":false,"isPlayer":false},{"turnFaceType":0,"tileId":4,"isAdvance":false,"isInvert":true,"isRope":false,"isStone":false,"isPlayer":false},{"turnFaceType":0,"tileId":1,"isAdvance":true,"isInvert":true,"isRope":false,"isStone":false,"isPlayer":false},{"turnFaceType":0,"tileId":1,"isAdvance":true,"isInvert":true,"isRope":false,"isStone":false,"isPlayer":false},{"turnFaceType":0,"tileId":5,"isAdvance":false,"isInvert":false,"isRope":false,"isStone":false,"isPlayer":false},{"turnFaceType":0,"tileId":0,"isAdvance":false,"isInvert":false,"isRope":false,"isStone":false,"isPlayer":false},{"turnFaceType":0,"tileId":5,"isAdvance":false,"isInvert":false,"isRope":false,"isStone":false,"isPlayer":false},{"turnFaceType":0,"tileId":2,"isAdvance":true,"isInvert":false,"isRope":true,"isStone":false,"isPlayer":false},{"turnFaceType":0,"tileId":4,"isAdvance":false,"isInvert":true,"isRope":false,"isStone":false,"isPlayer":false},{"turnFaceType":0,"tileId":1,"isAdvance":true,"isInvert":true,"isRope":false,"isStone":false,"isPlayer":false},{"turnFaceType":0,"tileId":4,"isAdvance":false,"isInvert":true,"isRope":false,"isStone":false,"isPlayer":false},{"turnFaceType":0,"tileId":1,"isAdvance":true,"isInvert":true,"isRope":false,"isStone":false,"isPlayer":false},{"turnFaceType":0,"tileId":5,"isAdvance":false,"isInvert":false,"isRope":false,"isStone":false,"isPlayer":false},{"turnFaceType":0,"tileId":0,"isAdvance":false,"isInvert":false,"isRope":false,"isStone":false,"isPlayer":false},{"turnFaceType":0,"tileId":5,"isAdvance":false,"isInvert":false,"isRope":false,"isStone":false,"isPlayer":false},{"turnFaceType":0,"tileId":5,"isAdvance":false,"isInvert":false,"isRope":false,"isStone":false,"isPlayer":false},{"turnFaceType":0,"tileId":5,"isAdvance":false,"isInvert":false,"isRope":false,"isStone":false,"isPlayer":false},{"turnFaceType":0,"tileId":5,"isAdvance":false,"isInvert":false,"isRope":false,"isStone":false,"isPlayer":false},{"turnFaceType":0,"tileId":5,"isAdvance":false,"isInvert":false,"isRope":false,"isStone":false,"isPlayer":false},{"turnFaceType":0,"tileId":5,"isAdvance":false,"isInvert":false,"isRope":false,"isStone":false,"isPlayer":false},{"turnFaceType":0,"tileId":5,"isAdvance":false,"isInvert":false,"isRope":false,"isStone":false,"isPlayer":false},{"turnFaceType":0,"tileId":0,"isAdvance":false,"isInvert":false,"isRope":false,"isStone":false,"isPlayer":false}]}